mkdocs_ipynb/__init__.py
mkdocs_ipynb/_core.py
mkdocs_ipynb-0.1.1.dist-info/METADATA
mkdocs_ipynb-0.1.1.dist-info/WHEEL
mkdocs_ipynb-0.1.1.dist-info/entry_points.txt
mkdocs_ipynb-0.1.1.dist-info/licenses/LICENSE
mkdocs_ipynb-0.1.1.dist-info/RECORD
