Metadata-Version: 2.4
Name: mkdocs_ipynb
Version: 0.1.1
Summary: A simple ipynb->md converter for MkDocs
Project-URL: repository, https://github.com/patrick-kidger/mkdocs_ipynb
Author-email: Patrick Kidger <contact@kidger.site>
License:                                  Apache License
License-File: LICENSE
Keywords: ipynb,jupyter,markdown,md,mkdocs
Classifier: Development Status :: 3 - Alpha
Classifier: License :: OSI Approved :: Apache Software License
Classifier: Natural Language :: English
Classifier: Programming Language :: Python :: 3
Requires-Python: >=3.10
Requires-Dist: mkdocs>=1.6.1
Provides-Extra: dev
Requires-Dist: pre-commit; extra == 'dev'
